rockstarter/__init__.py
rockstarter/commands.py
rockstarter/src/.env.sample
rockstarter/src/manage.py
rockstarter/src/requirements.txt
rockstarter/src/config/__init__.py
rockstarter/src/config/asgi.py
rockstarter/src/config/settings.py
rockstarter/src/config/urls.py
rockstarter/src/config/wsgi.py
rockstarter/src/logs/__init__
rockstarter/src/public/__init__
rockstarter/src/public/static/staticfiles.json
rockstarter/src/public/static/admin/css/autocomplete.4a81fc4242d0.css
rockstarter/src/public/static/admin/css/autocomplete.4a81fc4242d0.css.gz
rockstarter/src/public/static/admin/css/autocomplete.css
rockstarter/src/public/static/admin/css/autocomplete.css.gz
rockstarter/src/public/static/admin/css/base.523eb49842a7.css
rockstarter/src/public/static/admin/css/base.523eb49842a7.css.gz
rockstarter/src/public/static/admin/css/base.css
rockstarter/src/public/static/admin/css/base.css.gz
rockstarter/src/public/static/admin/css/changelists.9237a1ac391b.css
rockstarter/src/public/static/admin/css/changelists.9237a1ac391b.css.gz
rockstarter/src/public/static/admin/css/changelists.css
rockstarter/src/public/static/admin/css/changelists.css.gz
rockstarter/src/public/static/admin/css/dark_mode.css
rockstarter/src/public/static/admin/css/dark_mode.css.gz
rockstarter/src/public/static/admin/css/dark_mode.ef27a31af300.css
rockstarter/src/public/static/admin/css/dark_mode.ef27a31af300.css.gz
rockstarter/src/public/static/admin/css/dashboard.css
rockstarter/src/public/static/admin/css/dashboard.css.gz
rockstarter/src/public/static/admin/css/dashboard.e90f2068217b.css
rockstarter/src/public/static/admin/css/dashboard.e90f2068217b.css.gz
rockstarter/src/public/static/admin/css/forms.c14e1cb06392.css
rockstarter/src/public/static/admin/css/forms.c14e1cb06392.css.gz
rockstarter/src/public/static/admin/css/forms.css
rockstarter/src/public/static/admin/css/forms.css.gz
rockstarter/src/public/static/admin/css/login.586129c60a93.css
rockstarter-0.1.4.dist-info/LICENSE
rockstarter-0.1.4.dist-info/METADATA
rockstarter-0.1.4.dist-info/WHEEL
rockstarter-0.1.4.dist-info/entry_points.txt
rockstarter-0.1.4.dist-info/top_level.txt
rockstarter-0.1.4.dist-info/RECORD
