Metadata-Version: 2.1
Name: rockstarter
Version: 0.1.4
Summary: A simple tool to create django-ready project
Home-page: https://github.com/koderstory/django-rockstarter
Author: Koderstory
Author-email: hello@koderstory.com
Classifier: Programming Language :: Python :: 3
Classifier: License :: OSI Approved :: MIT License
Classifier: Operating System :: OS Independent
Requires-Python: >=3.6
License-File: LICENSE
Requires-Dist: Django >=4.2.15
Requires-Dist: asgiref ==3.8.1
Requires-Dist: django-environ ==0.11.2
Requires-Dist: sqlparse ==0.5.1
Requires-Dist: whitenoise ==6.7.0
Requires-Dist: gunicorn ==23.0.0
